mlgeo/__init__.py
mlgeo/datasets.py
mlgeo-0.0.3.dist-info/LICENSE.txt
mlgeo-0.0.3.dist-info/METADATA
mlgeo-0.0.3.dist-info/WHEEL
mlgeo-0.0.3.dist-info/top_level.txt
mlgeo-0.0.3.dist-info/RECORD
