Metadata-Version: 2.1
Name: mlgeo
Version: 0.0.3
Summary: Repository for Machine Learning in Geotechnics
Home-page: https://github.com/groundworkai/mlgeo
Author: Nick Machairas
Author-email: nick@groundwork.ai
License: UNKNOWN
Platform: UNKNOWN
Classifier: Programming Language :: Python :: 3
Classifier: License :: Other/Proprietary License
Classifier: Operating System :: OS Independent
Requires-Python: >=3.7
Requires-Dist: numpy (>=1.19)
